pystarter/__init__.py
pystarter/command_line.py
pystarter/license.py
pystarter/pystarter.py
pystarter/test.py
PyStarter-1.5.1.dist-info/LICENSE.txt
PyStarter-1.5.1.dist-info/METADATA
PyStarter-1.5.1.dist-info/WHEEL
PyStarter-1.5.1.dist-info/entry_points.txt
PyStarter-1.5.1.dist-info/top_level.txt
PyStarter-1.5.1.dist-info/RECORD
