Metadata-Version: 2.1
Name: PyStarter
Version: 1.5.1
Summary: A program to help you start python and git projects with file creations
Home-page: https://github.com/RafaelCenzano/PyStarter
Author: Rafael Cenzano
Author-email: savagecoder77@gmail.com
Maintainer: Rafael Cenzano
Maintainer-email: savagecoder77@gmail.com
License: UNKNOWN
Project-URL: Bug Reports, https://github.com/RafaelCenzano/PyStarter/issues
Project-URL: Source, https://github.com/RafaelCenzano/PyStarter
Keywords: pystarter git python
Platform: UNKNOWN
Classifier: Development Status :: 5 - Production/Stable
Classifier: Intended Audience :: Developers
Classifier: Topic :: Software Development :: Build Tools
Classifier: License :: OSI Approved :: MIT License
Classifier: Programming Language :: Python :: 3
Classifier: Programming Language :: Python :: 3.4
Classifier: Programming Language :: Python :: 3.5
Classifier: Programming Language :: Python :: 3.6
Classifier: Programming Language :: Python :: 3.7
Classifier: Programming Language :: Python :: 3.8
Requires-Python: >=3.4
